exh/__init__.py
exh/alternatives.py
exh/exhaust.py
exh/options.py
exh/scales.py
exh/exts/focus/__init__.py
exh/exts/focus/formula.py
exh/exts/focus/scales.py
exh/exts/gq/__init__.py
exh/fol/__init__.py
exh/fol/quantifier.py
exh/model/__init__.py
exh/model/exceptions.py
exh/model/model.py
exh/model/options.py
exh/model/vars.py
exh/prop/__init__.py
exh/prop/display.py
exh/prop/evaluate.py
exh/prop/formula.py
exh/prop/predicate.py
exh/prop/simplify.py
exh/utils/__init__.py
exh/utils/table.py
Exh-1.1.2.dist-info/LICENSE.txt
Exh-1.1.2.dist-info/METADATA
Exh-1.1.2.dist-info/WHEEL
Exh-1.1.2.dist-info/top_level.txt
Exh-1.1.2.dist-info/zip-safe
Exh-1.1.2.dist-info/RECORD
