Metadata-Version: 2.1
Name: Exh
Version: 1.1.2
Summary: Computes innocent exclusion/inclusions exhaustivity
Home-page: http://github.com/KenyC/Exh
Author: Keny Chatain
Author-email: kchatain@mit.edu
License: MIT
Platform: UNKNOWN
Requires-Dist: numpy
Requires-Dist: IPython
